{"page":45,"total_pages":126,"total_albums":15003,"albums":[{"id":"221393001","title":"F163","cover":"/api/image/rmqc/fb7df928/medium.jpg","images":[{"small":"/api/image/rmqc/fb7df928/medium.jpg","big":"/api/image/rmqc/fb7df928/medium.jpg"}]},{"id":"221392947","title":"7742844","cover":"/api/image/rmqc/678f7d0c/medium.jpg","images":[{"small":"/api/image/rmqc/678f7d0c/medium.jpg","big":"/api/image/rmqc/678f7d0c/medium.jpg"}]},{"id":"221391166","title":"7742844","cover":"/api/image/rmqc/9dddf779/medium.jpg","images":[{"small":"/api/image/rmqc/9dddf779/medium.jpg","big":"/api/image/rmqc/9dddf779/medium.jpg"}]},{"id":"221391156","title":"F163","cover":"/api/image/rmqc/69271d7c/medium.jpg","images":[{"small":"/api/image/rmqc/69271d7c/medium.jpg","big":"/api/image/rmqc/69271d7c/medium.jpg"}]},{"id":"221391150","title":"6885801","cover":"/api/image/rmqc/413d7b61/medium.jpg","images":[{"small":"/api/image/rmqc/413d7b61/medium.jpg","big":"/api/image/rmqc/413d7b61/medium.jpg"}]},{"id":"221391130","title":"2317586","cover":"/api/image/rmqc/e622aeff/medium.jpg","images":[{"small":"/api/image/rmqc/e622aeff/medium.jpg","big":"/api/image/rmqc/e622aeff/medium.jpg"}]},{"id":"221391122","title":"8188154","cover":"/api/image/rmqc/d1f91b0c/medium.jpg","images":[{"small":"/api/image/rmqc/d1f91b0c/medium.jpg","big":"/api/image/rmqc/d1f91b0c/medium.jpg"}]},{"id":"221391110","title":"7742844","cover":"/api/image/rmqc/d0e9fe5d/medium.jpg","images":[{"small":"/api/image/rmqc/d0e9fe5d/medium.jpg","big":"/api/image/rmqc/d0e9fe5d/medium.jpg"}]},{"id":"221391102","title":"3307904","cover":"/api/image/rmqc/77fe60fc/medium.jpg","images":[{"small":"/api/image/rmqc/77fe60fc/medium.jpg","big":"/api/image/rmqc/77fe60fc/medium.jpg"}]},{"id":"221391087","title":"2387404","cover":"/api/image/rmqc/e2670fad/medium.jpg","images":[{"small":"/api/image/rmqc/e2670fad/medium.jpg","big":"/api/image/rmqc/e2670fad/medium.jpg"}]},{"id":"221391075","title":"6802539","cover":"/api/image/rmqc/f64396f1/medium.jpg","images":[{"small":"/api/image/rmqc/f64396f1/medium.jpg","big":"/api/image/rmqc/f64396f1/medium.jpg"}]},{"id":"221391065","title":"7019147","cover":"/api/image/rmqc/723195c0/medium.jpg","images":[{"small":"/api/image/rmqc/723195c0/medium.jpg","big":"/api/image/rmqc/723195c0/medium.jpg"}]},{"id":"221391053","title":"9495203","cover":"/api/image/rmqc/17dccddb/medium.jpg","images":[{"small":"/api/image/rmqc/17dccddb/medium.jpg","big":"/api/image/rmqc/17dccddb/medium.jpg"}]},{"id":"221391042","title":"2756761","cover":"/api/image/rmqc/02bd243b/medium.jpg","images":[{"small":"/api/image/rmqc/02bd243b/medium.jpg","big":"/api/image/rmqc/02bd243b/medium.jpg"}]},{"id":"221391026","title":"4985116","cover":"/api/image/rmqc/eb220500/medium.jpg","images":[{"small":"/api/image/rmqc/eb220500/medium.jpg","big":"/api/image/rmqc/eb220500/medium.jpg"}]},{"id":"221388445","title":"4985116","cover":"/api/image/rmqc/87f815f2/medium.jpg","images":[{"small":"/api/image/rmqc/87f815f2/medium.jpg","big":"/api/image/rmqc/87f815f2/medium.jpg"}]},{"id":"221388429","title":"5304665","cover":"/api/image/rmqc/6ccbad64/medium.jpg","images":[{"small":"/api/image/rmqc/6ccbad64/medium.jpg","big":"/api/image/rmqc/6ccbad64/medium.jpg"}]},{"id":"221388410","title":"1623883","cover":"/api/image/rmqc/29d3b045/medium.jpg","images":[{"small":"/api/image/rmqc/29d3b045/medium.jpg","big":"/api/image/rmqc/29d3b045/medium.jpg"}]},{"id":"221388397","title":"8990018","cover":"/api/image/rmqc/b010caec/medium.jpg","images":[{"small":"/api/image/rmqc/b010caec/medium.jpg","big":"/api/image/rmqc/b010caec/medium.jpg"}]},{"id":"221388380","title":"4374779","cover":"/api/image/rmqc/3dd30e5d/medium.jpg","images":[{"small":"/api/image/rmqc/3dd30e5d/medium.jpg","big":"/api/image/rmqc/3dd30e5d/medium.jpg"}]},{"id":"221388370","title":"9887770","cover":"/api/image/rmqc/550968ea/medium.jpg","images":[{"small":"/api/image/rmqc/550968ea/medium.jpg","big":"/api/image/rmqc/550968ea/medium.jpg"}]},{"id":"221388360","title":"2729646","cover":"/api/image/rmqc/8d7e0cb9/medium.jpg","images":[{"small":"/api/image/rmqc/8d7e0cb9/medium.jpg","big":"/api/image/rmqc/8d7e0cb9/medium.jpg"}]},{"id":"221388344","title":"8589368","cover":"/api/image/rmqc/1ed70555/medium.jpg","images":[{"small":"/api/image/rmqc/1ed70555/medium.jpg","big":"/api/image/rmqc/1ed70555/medium.jpg"}]},{"id":"221388324","title":"7251208","cover":"/api/image/rmqc/a64be06e/medium.jpg","images":[{"small":"/api/image/rmqc/a64be06e/medium.jpg","big":"/api/image/rmqc/a64be06e/medium.jpg"}]},{"id":"221388309","title":"7270954","cover":"/api/image/rmqc/3b45eff9/medium.jpg","images":[{"small":"/api/image/rmqc/3b45eff9/medium.jpg","big":"/api/image/rmqc/3b45eff9/medium.jpg"}]},{"id":"221388292","title":"5806266","cover":"/api/image/rmqc/523f7645/medium.jpg","images":[{"small":"/api/image/rmqc/523f7645/medium.jpg","big":"/api/image/rmqc/523f7645/medium.jpg"}]},{"id":"221388258","title":"3215931","cover":"/api/image/rmqc/cfd480f9/medium.jpg","images":[{"small":"/api/image/rmqc/cfd480f9/medium.jpg","big":"/api/image/rmqc/cfd480f9/medium.jpg"}]},{"id":"221388244","title":"2644603","cover":"/api/image/rmqc/4364735d/medium.jpg","images":[{"small":"/api/image/rmqc/4364735d/medium.jpg","big":"/api/image/rmqc/4364735d/medium.jpg"}]},{"id":"221388225","title":"7409958","cover":"/api/image/rmqc/b051e2c0/medium.jpg","images":[{"small":"/api/image/rmqc/b051e2c0/medium.jpg","big":"/api/image/rmqc/b051e2c0/medium.jpg"}]},{"id":"221388209","title":"8609070","cover":"/api/image/rmqc/369e4600/medium.jpg","images":[{"small":"/api/image/rmqc/369e4600/medium.jpg","big":"/api/image/rmqc/369e4600/medium.jpg"}]},{"id":"221388193","title":"2713648","cover":"/api/image/rmqc/01949991/medium.jpg","images":[{"small":"/api/image/rmqc/01949991/medium.jpg","big":"/api/image/rmqc/01949991/medium.jpg"}]},{"id":"221388176","title":"5172473","cover":"/api/image/rmqc/f92a9d0d/medium.jpg","images":[{"small":"/api/image/rmqc/f92a9d0d/medium.jpg","big":"/api/image/rmqc/f92a9d0d/medium.jpg"}]},{"id":"221388158","title":"7270954","cover":"/api/image/rmqc/22cbd6a0/medium.jpg","images":[{"small":"/api/image/rmqc/22cbd6a0/medium.jpg","big":"/api/image/rmqc/22cbd6a0/medium.jpg"}]},{"id":"221388134","title":"7270954","cover":"/api/image/rmqc/8d0479a5/medium.jpg","images":[{"small":"/api/image/rmqc/8d0479a5/medium.jpg","big":"/api/image/rmqc/8d0479a5/medium.jpg"}]},{"id":"221388116","title":"3611390","cover":"/api/image/rmqc/6572c385/medium.jpg","images":[{"small":"/api/image/rmqc/6572c385/medium.jpg","big":"/api/image/rmqc/6572c385/medium.jpg"}]},{"id":"221388105","title":"5566706","cover":"/api/image/rmqc/5e39134d/medium.jpg","images":[{"small":"/api/image/rmqc/5e39134d/medium.jpg","big":"/api/image/rmqc/5e39134d/medium.jpg"}]},{"id":"221388066","title":"5057743","cover":"/api/image/rmqc/08e80690/medium.jpg","images":[{"small":"/api/image/rmqc/08e80690/medium.jpg","big":"/api/image/rmqc/08e80690/medium.jpg"}]},{"id":"221388050","title":"3898295","cover":"/api/image/rmqc/e35cf435/medium.jpg","images":[{"small":"/api/image/rmqc/e35cf435/medium.jpg","big":"/api/image/rmqc/e35cf435/medium.jpg"}]},{"id":"221388035","title":"8648253","cover":"/api/image/rmqc/da18c17b/medium.jpg","images":[{"small":"/api/image/rmqc/da18c17b/medium.jpg","big":"/api/image/rmqc/da18c17b/medium.jpg"}]},{"id":"221388012","title":"3933702","cover":"/api/image/rmqc/6667b52b/medium.jpg","images":[{"small":"/api/image/rmqc/6667b52b/medium.jpg","big":"/api/image/rmqc/6667b52b/medium.jpg"}]},{"id":"221387993","title":"5806266","cover":"/api/image/rmqc/f89a8cf0/medium.jpg","images":[{"small":"/api/image/rmqc/f89a8cf0/medium.jpg","big":"/api/image/rmqc/f89a8cf0/medium.jpg"}]},{"id":"221387980","title":"7124650","cover":"/api/image/rmqc/4d20d593/medium.jpg","images":[{"small":"/api/image/rmqc/4d20d593/medium.jpg","big":"/api/image/rmqc/4d20d593/medium.jpg"}]},{"id":"221387962","title":"8605056","cover":"/api/image/rmqc/0c822b5f/medium.jpg","images":[{"small":"/api/image/rmqc/0c822b5f/medium.jpg","big":"/api/image/rmqc/0c822b5f/medium.jpg"}]},{"id":"221387941","title":"8039635","cover":"/api/image/rmqc/e5d3be86/medium.jpg","images":[{"small":"/api/image/rmqc/e5d3be86/medium.jpg","big":"/api/image/rmqc/e5d3be86/medium.jpg"}]},{"id":"221387847","title":"5279413","cover":"/api/image/rmqc/ac2168f3/medium.jpg","images":[{"small":"/api/image/rmqc/ac2168f3/medium.jpg","big":"/api/image/rmqc/ac2168f3/medium.jpg"}]},{"id":"221387826","title":"3973361","cover":"/api/image/rmqc/798e5d0f/medium.jpg","images":[{"small":"/api/image/rmqc/798e5d0f/medium.jpg","big":"/api/image/rmqc/798e5d0f/medium.jpg"}]},{"id":"221387799","title":"9903941","cover":"/api/image/rmqc/d28f5e19/medium.jpg","images":[{"small":"/api/image/rmqc/d28f5e19/medium.jpg","big":"/api/image/rmqc/d28f5e19/medium.jpg"}]},{"id":"221387781","title":"5806266","cover":"/api/image/rmqc/2c0310c7/medium.jpg","images":[{"small":"/api/image/rmqc/2c0310c7/medium.jpg","big":"/api/image/rmqc/2c0310c7/medium.jpg"}]},{"id":"221387760","title":"3309427","cover":"/api/image/rmqc/7121802c/medium.jpg","images":[{"small":"/api/image/rmqc/7121802c/medium.jpg","big":"/api/image/rmqc/7121802c/medium.jpg"}]},{"id":"221387741","title":"2206109","cover":"/api/image/rmqc/ad32c273/medium.jpg","images":[{"small":"/api/image/rmqc/ad32c273/medium.jpg","big":"/api/image/rmqc/ad32c273/medium.jpg"}]},{"id":"221387721","title":"8615804","cover":"/api/image/rmqc/330a0ed3/medium.jpg","images":[{"small":"/api/image/rmqc/330a0ed3/medium.jpg","big":"/api/image/rmqc/330a0ed3/medium.jpg"}]},{"id":"221387692","title":"2907009","cover":"/api/image/rmqc/97018e1d/medium.jpg","images":[{"small":"/api/image/rmqc/97018e1d/medium.jpg","big":"/api/image/rmqc/97018e1d/medium.jpg"}]},{"id":"221387640","title":"5739122","cover":"/api/image/rmqc/3c38ae86/medium.jpg","images":[{"small":"/api/image/rmqc/3c38ae86/medium.jpg","big":"/api/image/rmqc/3c38ae86/medium.jpg"}]},{"id":"221387620","title":"5324745","cover":"/api/image/rmqc/21953ae7/medium.jpg","images":[{"small":"/api/image/rmqc/21953ae7/medium.jpg","big":"/api/image/rmqc/21953ae7/medium.jpg"}]},{"id":"221387599","title":"3988382","cover":"/api/image/rmqc/e757a4c9/medium.jpg","images":[{"small":"/api/image/rmqc/e757a4c9/medium.jpg","big":"/api/image/rmqc/e757a4c9/medium.jpg"}]},{"id":"221387575","title":"4465194","cover":"/api/image/rmqc/557637f3/medium.jpg","images":[{"small":"/api/image/rmqc/557637f3/medium.jpg","big":"/api/image/rmqc/557637f3/medium.jpg"}]},{"id":"221387560","title":"4761085","cover":"/api/image/rmqc/1a51209b/medium.jpg","images":[{"small":"/api/image/rmqc/1a51209b/medium.jpg","big":"/api/image/rmqc/1a51209b/medium.jpg"}]},{"id":"221387540","title":"3356907","cover":"/api/image/rmqc/d6f0268c/medium.jpg","images":[{"small":"/api/image/rmqc/d6f0268c/medium.jpg","big":"/api/image/rmqc/d6f0268c/medium.jpg"}]},{"id":"221387516","title":"9292519","cover":"/api/image/rmqc/396f7ad2/medium.jpg","images":[{"small":"/api/image/rmqc/396f7ad2/medium.jpg","big":"/api/image/rmqc/396f7ad2/medium.jpg"}]},{"id":"221387498","title":"2575149","cover":"/api/image/rmqc/9b5813ee/medium.jpg","images":[{"small":"/api/image/rmqc/9b5813ee/medium.jpg","big":"/api/image/rmqc/9b5813ee/medium.jpg"}]},{"id":"221387476","title":"2105790","cover":"/api/image/rmqc/e17c8016/medium.jpg","images":[{"small":"/api/image/rmqc/e17c8016/medium.jpg","big":"/api/image/rmqc/e17c8016/medium.jpg"}]},{"id":"221387460","title":"3307904","cover":"/api/image/rmqc/c3a9a1ae/medium.jpg","images":[{"small":"/api/image/rmqc/c3a9a1ae/medium.jpg","big":"/api/image/rmqc/c3a9a1ae/medium.jpg"}]},{"id":"221387445","title":"7896519","cover":"/api/image/rmqc/f7863274/medium.jpg","images":[{"small":"/api/image/rmqc/f7863274/medium.jpg","big":"/api/image/rmqc/f7863274/medium.jpg"}]},{"id":"221387420","title":"7790188","cover":"/api/image/rmqc/449ed002/medium.jpg","images":[{"small":"/api/image/rmqc/449ed002/medium.jpg","big":"/api/image/rmqc/449ed002/medium.jpg"}]},{"id":"221387397","title":"9390974","cover":"/api/image/rmqc/39c58a42/medium.jpg","images":[{"small":"/api/image/rmqc/39c58a42/medium.jpg","big":"/api/image/rmqc/39c58a42/medium.jpg"}]},{"id":"221387367","title":"9895144","cover":"/api/image/rmqc/3386b6f2/medium.jpg","images":[{"small":"/api/image/rmqc/3386b6f2/medium.jpg","big":"/api/image/rmqc/3386b6f2/medium.jpg"}]},{"id":"221387342","title":"7896519","cover":"/api/image/rmqc/79e64477/medium.jpg","images":[{"small":"/api/image/rmqc/79e64477/medium.jpg","big":"/api/image/rmqc/79e64477/medium.jpg"}]},{"id":"221387314","title":"6885801","cover":"/api/image/rmqc/c76e4e37/medium.jpg","images":[{"small":"/api/image/rmqc/c76e4e37/medium.jpg","big":"/api/image/rmqc/c76e4e37/medium.jpg"}]},{"id":"221387291","title":"0528491","cover":"/api/image/rmqc/82d65ea4/medium.jpg","images":[{"small":"/api/image/rmqc/82d65ea4/medium.jpg","big":"/api/image/rmqc/82d65ea4/medium.jpg"}]},{"id":"221387260","title":"5334191","cover":"/api/image/rmqc/71cfbc9a/medium.jpg","images":[{"small":"/api/image/rmqc/71cfbc9a/medium.jpg","big":"/api/image/rmqc/71cfbc9a/medium.jpg"}]},{"id":"221387234","title":"5286127","cover":"/api/image/rmqc/6b304be3/medium.jpg","images":[{"small":"/api/image/rmqc/6b304be3/medium.jpg","big":"/api/image/rmqc/6b304be3/medium.jpg"}]},{"id":"221387087","title":"LJR","cover":"/api/image/rmqc/0c9105c0/medium.jpg","images":[{"small":"/api/image/rmqc/0c9105c0/medium.jpg","big":"/api/image/rmqc/0c9105c0/medium.jpg"}]},{"id":"221287051","title":"2008000","cover":"/api/image/rmqc/788ee570/medium.jpg","images":[{"small":"/api/image/rmqc/788ee570/medium.jpg","big":"/api/image/rmqc/788ee570/medium.jpg"}]},{"id":"221287042","title":"2317586","cover":"/api/image/rmqc/edd51998/medium.jpg","images":[{"small":"/api/image/rmqc/edd51998/medium.jpg","big":"/api/image/rmqc/edd51998/medium.jpg"}]},{"id":"221287031","title":"3045899","cover":"/api/image/rmqc/a79200cc/medium.jpg","images":[{"small":"/api/image/rmqc/a79200cc/medium.jpg","big":"/api/image/rmqc/a79200cc/medium.jpg"}]},{"id":"221287022","title":"2105790","cover":"/api/image/rmqc/bc9632a0/medium.jpg","images":[{"small":"/api/image/rmqc/bc9632a0/medium.jpg","big":"/api/image/rmqc/bc9632a0/medium.jpg"}]},{"id":"221287009","title":"1232011","cover":"/api/image/rmqc/469781f4/medium.jpg","images":[{"small":"/api/image/rmqc/469781f4/medium.jpg","big":"/api/image/rmqc/469781f4/medium.jpg"}]},{"id":"221286998","title":"3813485","cover":"/api/image/rmqc/74893300/medium.jpg","images":[{"small":"/api/image/rmqc/74893300/medium.jpg","big":"/api/image/rmqc/74893300/medium.jpg"}]},{"id":"221286985","title":"3813485","cover":"/api/image/rmqc/e0e2a62c/medium.jpg","images":[{"small":"/api/image/rmqc/e0e2a62c/medium.jpg","big":"/api/image/rmqc/e0e2a62c/medium.jpg"}]},{"id":"221286975","title":"6880807","cover":"/api/image/rmqc/2607c7b4/medium.jpg","images":[{"small":"/api/image/rmqc/2607c7b4/medium.jpg","big":"/api/image/rmqc/2607c7b4/medium.jpg"}]},{"id":"221286962","title":"5871289","cover":"/api/image/rmqc/eed62afa/medium.jpg","images":[{"small":"/api/image/rmqc/eed62afa/medium.jpg","big":"/api/image/rmqc/eed62afa/medium.jpg"}]},{"id":"221286956","title":"9903941","cover":"/api/image/rmqc/26655cd3/medium.jpg","images":[{"small":"/api/image/rmqc/26655cd3/medium.jpg","big":"/api/image/rmqc/26655cd3/medium.jpg"}]},{"id":"221286944","title":"2239085","cover":"/api/image/rmqc/f8559258/medium.jpg","images":[{"small":"/api/image/rmqc/f8559258/medium.jpg","big":"/api/image/rmqc/f8559258/medium.jpg"}]},{"id":"221286934","title":"8001985","cover":"/api/image/rmqc/25b946c6/medium.jpg","images":[{"small":"/api/image/rmqc/25b946c6/medium.jpg","big":"/api/image/rmqc/25b946c6/medium.jpg"}]},{"id":"221286922","title":"0817305","cover":"/api/image/rmqc/061ccb8e/medium.jpg","images":[{"small":"/api/image/rmqc/061ccb8e/medium.jpg","big":"/api/image/rmqc/061ccb8e/medium.jpg"}]},{"id":"221284957","title":"8913977","cover":"/api/image/rmqc/b62acc41/medium.jpg","images":[{"small":"/api/image/rmqc/b62acc41/medium.jpg","big":"/api/image/rmqc/b62acc41/medium.jpg"}]},{"id":"221284946","title":"6133439","cover":"/api/image/rmqc/523f331a/medium.jpg","images":[{"small":"/api/image/rmqc/523f331a/medium.jpg","big":"/api/image/rmqc/523f331a/medium.jpg"}]},{"id":"221284930","title":"7080468","cover":"/api/image/rmqc/4e92eb8a/medium.jpg","images":[{"small":"/api/image/rmqc/4e92eb8a/medium.jpg","big":"/api/image/rmqc/4e92eb8a/medium.jpg"}]},{"id":"221284764","title":"9527724","cover":"/api/image/rmqc/b5b69618/medium.jpg","images":[{"small":"/api/image/rmqc/b5b69618/medium.jpg","big":"/api/image/rmqc/b5b69618/medium.jpg"}]},{"id":"221284749","title":"3982968","cover":"/api/image/rmqc/3e4d13a0/medium.jpg","images":[{"small":"/api/image/rmqc/3e4d13a0/medium.jpg","big":"/api/image/rmqc/3e4d13a0/medium.jpg"}]},{"id":"221284736","title":"8003012","cover":"/api/image/rmqc/bde27132/medium.jpg","images":[{"small":"/api/image/rmqc/bde27132/medium.jpg","big":"/api/image/rmqc/bde27132/medium.jpg"}]},{"id":"221284714","title":"7332960","cover":"/api/image/rmqc/900f0152/medium.jpg","images":[{"small":"/api/image/rmqc/900f0152/medium.jpg","big":"/api/image/rmqc/900f0152/medium.jpg"}]},{"id":"221284702","title":"8931096","cover":"/api/image/rmqc/947f8880/medium.jpg","images":[{"small":"/api/image/rmqc/947f8880/medium.jpg","big":"/api/image/rmqc/947f8880/medium.jpg"}]},{"id":"221284692","title":"3095643","cover":"/api/image/rmqc/c9e323fc/medium.jpg","images":[{"small":"/api/image/rmqc/c9e323fc/medium.jpg","big":"/api/image/rmqc/c9e323fc/medium.jpg"}]},{"id":"221284674","title":"0814892","cover":"/api/image/rmqc/761917d4/medium.jpg","images":[{"small":"/api/image/rmqc/761917d4/medium.jpg","big":"/api/image/rmqc/761917d4/medium.jpg"}]},{"id":"221284654","title":"7332960","cover":"/api/image/rmqc/c3eca1ab/medium.jpg","images":[{"small":"/api/image/rmqc/c3eca1ab/medium.jpg","big":"/api/image/rmqc/c3eca1ab/medium.jpg"}]},{"id":"221283546","title":"7332960","cover":"/api/image/rmqc/54ccb438/medium.jpg","images":[{"small":"/api/image/rmqc/54ccb438/medium.jpg","big":"/api/image/rmqc/54ccb438/medium.jpg"}]},{"id":"221283529","title":"8001985","cover":"/api/image/rmqc/87f4ad4b/medium.jpg","images":[{"small":"/api/image/rmqc/87f4ad4b/medium.jpg","big":"/api/image/rmqc/87f4ad4b/medium.jpg"}]},{"id":"221283515","title":"6563564","cover":"/api/image/rmqc/8984e5ef/medium.jpg","images":[{"small":"/api/image/rmqc/8984e5ef/medium.jpg","big":"/api/image/rmqc/8984e5ef/medium.jpg"}]},{"id":"221283503","title":"5508931","cover":"/api/image/rmqc/3f65e2b3/medium.jpg","images":[{"small":"/api/image/rmqc/3f65e2b3/medium.jpg","big":"/api/image/rmqc/3f65e2b3/medium.jpg"}]},{"id":"221283486","title":"7539383","cover":"/api/image/rmqc/d0de18be/medium.jpg","images":[{"small":"/api/image/rmqc/d0de18be/medium.jpg","big":"/api/image/rmqc/d0de18be/medium.jpg"}]},{"id":"221283475","title":"1738983","cover":"/api/image/rmqc/c931cb63/medium.jpg","images":[{"small":"/api/image/rmqc/c931cb63/medium.jpg","big":"/api/image/rmqc/c931cb63/medium.jpg"}]},{"id":"221283465","title":"5322030","cover":"/api/image/rmqc/62333fdb/medium.jpg","images":[{"small":"/api/image/rmqc/62333fdb/medium.jpg","big":"/api/image/rmqc/62333fdb/medium.jpg"}]},{"id":"221283452","title":"5033599","cover":"/api/image/rmqc/b4b704df/medium.jpg","images":[{"small":"/api/image/rmqc/b4b704df/medium.jpg","big":"/api/image/rmqc/b4b704df/medium.jpg"}]},{"id":"221282245","title":"2819586","cover":"/api/image/rmqc/787c95cc/medium.jpg","images":[{"small":"/api/image/rmqc/787c95cc/medium.jpg","big":"/api/image/rmqc/787c95cc/medium.jpg"}]},{"id":"221282234","title":"4465194","cover":"/api/image/rmqc/234f0cdb/medium.jpg","images":[{"small":"/api/image/rmqc/234f0cdb/medium.jpg","big":"/api/image/rmqc/234f0cdb/medium.jpg"}]},{"id":"221282223","title":"shoddy","cover":"/api/image/rmqc/3eaa127b/medium.jpg","images":[{"small":"/api/image/rmqc/3eaa127b/medium.jpg","big":"/api/image/rmqc/3eaa127b/medium.jpg"}]},{"id":"221282213","title":"9190661","cover":"/api/image/rmqc/a6080377/medium.jpg","images":[{"small":"/api/image/rmqc/a6080377/medium.jpg","big":"/api/image/rmqc/a6080377/medium.jpg"}]},{"id":"221282201","title":"6608855","cover":"/api/image/rmqc/e0107ab2/medium.jpg","images":[{"small":"/api/image/rmqc/e0107ab2/medium.jpg","big":"/api/image/rmqc/e0107ab2/medium.jpg"}]},{"id":"221282187","title":"2213677","cover":"/api/image/rmqc/487d00b0/medium.jpg","images":[{"small":"/api/image/rmqc/487d00b0/medium.jpg","big":"/api/image/rmqc/487d00b0/medium.jpg"}]},{"id":"221282173","title":"8001985","cover":"/api/image/rmqc/3b87e84a/medium.jpg","images":[{"small":"/api/image/rmqc/3b87e84a/medium.jpg","big":"/api/image/rmqc/3b87e84a/medium.jpg"}]},{"id":"221282162","title":"8403244","cover":"/api/image/rmqc/a525e7a3/medium.jpg","images":[{"small":"/api/image/rmqc/a525e7a3/medium.jpg","big":"/api/image/rmqc/a525e7a3/medium.jpg"}]},{"id":"221282147","title":"6360377","cover":"/api/image/rmqc/3fcb3789/medium.jpg","images":[{"small":"/api/image/rmqc/3fcb3789/medium.jpg","big":"/api/image/rmqc/3fcb3789/medium.jpg"}]},{"id":"221282135","title":"1623883","cover":"/api/image/rmqc/53bccfb0/medium.jpg","images":[{"small":"/api/image/rmqc/53bccfb0/medium.jpg","big":"/api/image/rmqc/53bccfb0/medium.jpg"}]},{"id":"221282121","title":"7285457","cover":"/api/image/rmqc/c31a6ae6/medium.jpg","images":[{"small":"/api/image/rmqc/c31a6ae6/medium.jpg","big":"/api/image/rmqc/c31a6ae6/medium.jpg"}]},{"id":"221282108","title":"4904906","cover":"/api/image/rmqc/162d4054/medium.jpg","images":[{"small":"/api/image/rmqc/162d4054/medium.jpg","big":"/api/image/rmqc/162d4054/medium.jpg"}]},{"id":"221282094","title":"8190530","cover":"/api/image/rmqc/0e0e5040/medium.jpg","images":[{"small":"/api/image/rmqc/0e0e5040/medium.jpg","big":"/api/image/rmqc/0e0e5040/medium.jpg"}]},{"id":"221282065","title":"9903941","cover":"/api/image/rmqc/67c4b5fb/medium.jpg","images":[{"small":"/api/image/rmqc/67c4b5fb/medium.jpg","big":"/api/image/rmqc/67c4b5fb/medium.jpg"}]},{"id":"221282054","title":"7918202","cover":"/api/image/rmqc/abb74032/medium.jpg","images":[{"small":"/api/image/rmqc/abb74032/medium.jpg","big":"/api/image/rmqc/abb74032/medium.jpg"}]},{"id":"221282038","title":"7019477","cover":"/api/image/rmqc/e41cc658/medium.jpg","images":[{"small":"/api/image/rmqc/e41cc658/medium.jpg","big":"/api/image/rmqc/e41cc658/medium.jpg"}]}]}